pyumldiagrams/BaseDiagram.py
pyumldiagrams/Common.py
pyumldiagrams/CommonAbsolute.py
pyumldiagrams/Defaults.py
pyumldiagrams/Definitions.py
pyumldiagrams/IDiagramLine.py
pyumldiagrams/Internal.py
pyumldiagrams/UnsupportedException.py
pyumldiagrams/__init__.py
pyumldiagrams/_version.py
pyumldiagrams/py.typed
pyumldiagrams/image/ImageCommon.py
pyumldiagrams/image/ImageDiagram.py
pyumldiagrams/image/ImageFormat.py
pyumldiagrams/image/ImageLine.py
pyumldiagrams/image/__init__.py
pyumldiagrams/image/py.typed
pyumldiagrams/image/resources/__init__.py
pyumldiagrams/image/resources/py.typed
pyumldiagrams/pdf/FPDFExtended.py
pyumldiagrams/pdf/PdfCommon.py
pyumldiagrams/pdf/PdfDiagram.py
pyumldiagrams/pdf/PdfLine.py
pyumldiagrams/pdf/PdfLollipopInterface.py
pyumldiagrams/pdf/__init__.py
pyumldiagrams/pdf/py.typed
pyumldiagrams/pdf/resources/__init__.py
pyumldiagrams/pdf/resources/py.typed
pyumldiagrams/xmlsupport/AbstractToClassDefinition.py
pyumldiagrams/xmlsupport/SafeConversions.py
pyumldiagrams/xmlsupport/ShapeAttributes.py
pyumldiagrams/xmlsupport/ToClassDefinition.py
pyumldiagrams/xmlsupport/UnTangleLineDefinition.py
pyumldiagrams/xmlsupport/UnTangleNoteDefinition.py
pyumldiagrams/xmlsupport/UnTangleToClassDefinition.py
pyumldiagrams/xmlsupport/XmlConstants.py
pyumldiagrams/xmlsupport/__init__.py
pyumldiagrams/xmlsupport/py.typed
pyumldiagrams/xmlsupport/exceptions/MultiDocumentException.py
pyumldiagrams/xmlsupport/exceptions/NotClassDiagramException.py
pyumldiagrams/xmlsupport/exceptions/__init__.py
pyumldiagrams-3.1.20.dist-info/LICENSE
pyumldiagrams-3.1.20.dist-info/METADATA
pyumldiagrams-3.1.20.dist-info/WHEEL
pyumldiagrams-3.1.20.dist-info/top_level.txt
pyumldiagrams-3.1.20.dist-info/RECORD
