Metadata-Version: 2.1
Name: pyumldiagrams
Version: 3.1.20
Summary: Draw UML diagrams in various formats
Author-email: "Humberto A. Sanchez II" <Humbert.A.Sanchez.II@gmail.com>
Maintainer-email: "Humberto A. Sanchez II" <Humbert.A.Sanchez.II@gmail.com>
License: GNU AFFERO GENERAL PUBLIC LICENSE
Project-URL: Repository, https://github.com/hasii2011/pyumldiagrams
Keywords: pyut,UML,Diagrams,Python
License-File: LICENSE
Requires-Dist: fpdf2==2.7.7
Requires-Dist: Pillow==10.3.0
Requires-Dist: untangle==1.2.1
Requires-Dist: codeallybasic>=1.7.0
Requires-Dist: codeallyadvanced>=1.3.2
